odoo/addons/account_invoice_report_header_repeater/README.rst
odoo/addons/account_invoice_report_header_repeater/__init__.py
odoo/addons/account_invoice_report_header_repeater/__manifest__.py
odoo/addons/account_invoice_report_header_repeater/i18n/account_invoice_report_header_repeater.pot
odoo/addons/account_invoice_report_header_repeater/i18n/it.po
odoo/addons/account_invoice_report_header_repeater/readme/CONTRIBUTORS.rst
odoo/addons/account_invoice_report_header_repeater/readme/DESCRIPTION.rst
odoo/addons/account_invoice_report_header_repeater/static/description/icon.png
odoo/addons/account_invoice_report_header_repeater/static/description/index.html
odoo/addons/account_invoice_report_header_repeater/views/report_invoice.xml
odoo_addon_account_invoice_report_header_repeater-16.0.1.0.0.3.dist-info/METADATA
odoo_addon_account_invoice_report_header_repeater-16.0.1.0.0.3.dist-info/WHEEL
odoo_addon_account_invoice_report_header_repeater-16.0.1.0.0.3.dist-info/top_level.txt
odoo_addon_account_invoice_report_header_repeater-16.0.1.0.0.3.dist-info/RECORD
